mangaba_ai-1.0.0.dist-info/licenses/LICENSE
protocols/__init__.py
protocols/a2a.py
protocols/mcp.py
tests/__init__.py
tests/conftest.py
tests/test_a2a_protocol.py
tests/test_integration.py
tests/test_mangaba_agent.py
tests/test_mcp_protocol.py
utils/__init__.py
utils/logger.py
mangaba_ai-1.0.0.dist-info/METADATA
mangaba_ai-1.0.0.dist-info/WHEEL
mangaba_ai-1.0.0.dist-info/top_level.txt
mangaba_ai-1.0.0.dist-info/RECORD
