Metadata-Version: 2.4
Name: mangaba-ai
Version: 1.0.0
Summary: Agente de IA inteligente e versátil
Home-page: https://github.com/mangaba-ai/mangaba-ai
Author: Mangaba AI Team
Author-email: contato@mangaba.ai
Project-URL: Bug Reports, https://github.com/mangaba-ai/mangaba-ai/issues
Project-URL: Source, https://github.com/mangaba-ai/mangaba-ai
Project-URL: Documentation, https://github.com/mangaba-ai/mangaba-ai#readme
Keywords: ai,gemini,google,chatbot,artificial intelligence
Classifier: Development Status :: 4 - Beta
Classifier: Intended Audience :: Developers
Classifier: License :: OSI Approved :: MIT License
Classifier: Operating System :: OS Independent
Classifier: Programming Language :: Python :: 3
Classifier: Programming Language :: Python :: 3.8
Classifier: Programming Language :: Python :: 3.9
Classifier: Programming Language :: Python :: 3.10
Classifier: Programming Language :: Python :: 3.11
Classifier: Programming Language :: Python :: 3.12
Classifier: Topic :: Scientific/Engineering :: Artificial Intelligence
Classifier: Topic :: Software Development :: Libraries :: Python Modules
Requires-Python: >=3.8
License-File: LICENSE
Requires-Dist: google-generativeai>=0.3.0
Requires-Dist: python-dotenv>=0.19.0
Requires-Dist: loguru>=0.6.0
Requires-Dist: pydantic>=1.8.0
Requires-Dist: requests>=2.25.0
Requires-Dist: websockets>=10.0
Dynamic: author
Dynamic: author-email
Dynamic: classifier
Dynamic: description
Dynamic: description-content-type
Dynamic: home-page
Dynamic: keywords
Dynamic: license-file
Dynamic: project-url
Dynamic: requires-dist
Dynamic: requires-python
Dynamic: summary
